README.rst
setup.py
tests/__init__.py
tests/test_fields.py
tests/test_jsonschema.py
tests/test_schema.py
valipede/__init__.py
valipede/dateparsers.py
valipede/decorators.py
valipede/fields.py
valipede/jsonschema.py
valipede/schema.py
valipede.egg-info/PKG-INFO
valipede.egg-info/SOURCES.txt
valipede.egg-info/dependency_links.txt
valipede.egg-info/requires.txt
valipede.egg-info/top_level.txt